{
    "type": "FeatureCollection",
    "features": [
        {
            "type": "Feature",
            "geometry": {
                "type": "Point",
                "coordinates": [ 13.8, 52.4]
            },
            "label": "Tesla Gigafactory",
            "description": "Tesla Gigafactory"
        },
        {
            "type": "Feature",
            "geometry": {
                "type": "Point",
                "coordinates": [ 11.033333, 50.983334]
            },
            "label": "CATL Gigafactory",
            "description": "CATL Gigafactory"
        }
    ]
}